{
  "forecast_date": "2025-01",
  "point_forecast": 30205.3593781912,
  "confidence_interval": {
    "lower": 16341.89790999205,
    "upper": 44068.82084639034
  },
  "model_info": {
    "type": "SARIMA",
    "order": "(1, 1, 1)",
    "seasonal_order": "(0, 0, 0, 0)",
    "aic": 193.71093644846442,
    "bic": 194.3026101804731
  },
  "historical_data": [
    {
      "month": "2024-01",
      "revenue": 39580.51999999999
    },
    {
      "month": "2024-02",
      "revenue": 33189.33
    },
    {
      "month": "2024-03",
      "revenue": 30056.270000000008
    },
    {
      "month": "2024-04",
      "revenue": 44570.15000000002
    },
    {
      "month": "2024-05",
      "revenue": 33352.78999999999
    },
    {
      "month": "2024-06",
      "revenue": 23697.929999999993
    },
    {
      "month": "2024-07",
      "revenue": 28575.279999999995
    },
    {
      "month": "2024-08",
      "revenue": 29641.309999999998
    },
    {
      "month": "2024-09",
      "revenue": 42706.38
    },
    {
      "month": "2024-10",
      "revenue": 36942.34999999999
    },
    {
      "month": "2024-11",
      "revenue": 28402.150000000005
    },
    {
      "month": "2024-12",
      "revenue": 23030.160000000003
    }
  ]
}